{
  "name": "v1alpha1OptionIssuanceTransaction",
  "sanitized_name": "option_issuance_transaction",
  "schema_type": "type",
  "schema_def": {
    "type": "object",
    "example": {
      "issueDatetime": {
        "value": "2024-01-15T00:00:00Z"
      },
      "quantity": {
        "value": "10000"
      },
      "stockOptionType": "STOCK_OPTION_TYPE_ISO",
      "exercisePrice": {
        "currencyCode": {
          "value": "USD"
        },
        "amount": {
          "value": "1.50"
        }
      },
      "equityPlanId": "42",
      "expirationDatetime": {
        "value": "2034-01-15T00:00:00Z"
      }
    },
    "properties": {
      "issueDatetime": {
        "$ref": "#/components/schemas/v1alpha1Iso8601CompleteCalendarDateTime",
        "description": "The date and time the option grant was issued."
      },
      "quantity": {
        "$ref": "#/components/schemas/v1alpha1Decimal",
        "description": "The number of shares reserved from the equity plan share reserve."
      },
      "stockOptionType": {
        "$ref": "#/components/schemas/issuerstransactionsv1alpha1StockOptionType",
        "description": "The tax classification of the option grant. Determines the tax treatment based on the jurisdiction and plan type. See `StockOptionType` for all supported values."
      },
      "exercisePrice": {
        "$ref": "#/components/schemas/v1alpha1Money",
        "description": "The per-share price at which the holder can purchase the underlying shares."
      },
      "equityPlanId": {
        "type": "string",
        "description": "The identifier of the equity plan from which the option grant was issued.",
        "maxLength": 50
      },
      "shareClassId": {
        "type": "string",
        "description": "The identifier of the share class. May be absent if the plan has no associated share class.",
        "maxLength": 50
      },
      "expirationDatetime": {
        "$ref": "#/components/schemas/v1alpha1Iso8601CompleteCalendarDateTime",
        "description": "The date and time the option grant expires."
      },
      "vestingScheduleTemplateId": {
        "type": "string",
        "description": "The identifier of the vesting schedule template. May be absent if the grant has no vesting schedule.",
        "maxLength": 50
      }
    },
    "description": "The issuance transaction for an option grant. Represents the initial grant of options."
  },
  "endpoints": [],
  "referenced_by": [
    "v1alpha1OptionTransactionItem"
  ],
  "references": [
    "v1alpha1Iso8601CompleteCalendarDateTime",
    "v1alpha1Decimal",
    "issuerstransactionsv1alpha1StockOptionType",
    "v1alpha1Money"
  ],
  "output_path": "docs/types/option_issuance_transaction.md"
}